Metadata-Version: 2.1
Name: rustytable
Version: 0.1.1
Summary: A high-performance, feature-rich table formatting library
Home-page: https://github.com/jhhemal/rustytable
Author: Jahidul Hasan Hemal
Author-email: jahidulhasanhemal@gmail.com
Classifier: Programming Language :: Python :: 3
Classifier: Programming Language :: Rust
Classifier: License :: OSI Approved :: MIT License
Classifier: Operating System :: OS Independent
Classifier: Development Status :: 4 - Beta
Classifier: Intended Audience :: Developers
Classifier: Topic :: Software Development :: Libraries :: Python Modules
Requires-Python: >=3.6
License-File: LICENSE
